herpetologist/__init__.py
herpetologist-0.0.9.dist-info/METADATA
herpetologist-0.0.9.dist-info/WHEEL
herpetologist-0.0.9.dist-info/top_level.txt
herpetologist-0.0.9.dist-info/RECORD
